ssiamb/__init__.py
ssiamb/__main__.py
ssiamb/bracken.py
ssiamb/calling.py
ssiamb/cli.py
ssiamb/config.py
ssiamb/depth.py
ssiamb/errors.py
ssiamb/io_utils.py
ssiamb/mapping.py
ssiamb/models.py
ssiamb/provenance.py
ssiamb/qc.py
ssiamb/refdir.py
ssiamb/refseq.py
ssiamb/reuse.py
ssiamb/runner.py
ssiamb/tool_config.py
ssiamb/vcf_ops.py
ssiamb/version.py
ssiamb/config/defaults.yaml
ssiamb/config/tools.yaml
ssiamb-0.9.0.dist-info/METADATA
ssiamb-0.9.0.dist-info/WHEEL
ssiamb-0.9.0.dist-info/entry_points.txt
ssiamb-0.9.0.dist-info/licenses/LICENSE
ssiamb-0.9.0.dist-info/RECORD
