Metadata-Version: 2.4
Name: ssiamb
Version: 0.9.0
Summary: SSI Ambiguous Site Detection Tool
Project-URL: Homepage, https://github.com/ssi-dk/ssiamb
Project-URL: Repository, https://github.com/ssi-dk/ssiamb
Project-URL: Issues, https://github.com/ssi-dk/ssiamb/issues
Author-email: SSI Denmark <support@ssi.dk>
License-Expression: MIT
License-File: LICENSE
Keywords: bacterial-genomics,bioinformatics,genomics,mapping,variant-calling
Classifier: Development Status :: 3 - Alpha
Classifier: Intended Audience :: Science/Research
Classifier: License :: OSI Approved :: MIT License
Classifier: Programming Language :: Python :: 3
Classifier: Programming Language :: Python :: 3.12
Classifier: Programming Language :: Python :: 3.13
Classifier: Topic :: Scientific/Engineering :: Bio-Informatics
Requires-Python: >=3.12
Requires-Dist: biopython>=1.81
Requires-Dist: numpy>=1.24.0
Requires-Dist: pandas>=2.0.0
Requires-Dist: pysam>=0.21.0
Requires-Dist: pyyaml>=6.0
Requires-Dist: requests>=2.25.0
Requires-Dist: rich>=13.0.0
Requires-Dist: typer[all]>=0.9.0
Provides-Extra: dev
Requires-Dist: black>=23.0.0; extra == 'dev'
Requires-Dist: mypy>=1.5.0; extra == 'dev'
Requires-Dist: pandas-stubs; extra == 'dev'
Requires-Dist: pytest-cov>=4.0.0; extra == 'dev'
Requires-Dist: pytest>=7.0.0; extra == 'dev'
Requires-Dist: ruff>=0.1.0; extra == 'dev'
Requires-Dist: types-pyyaml; extra == 'dev'
Requires-Dist: types-requests; extra == 'dev'
